Metadata-Version: 2.1
Name: git-issue-reporter
Version: 1.1.0
Summary: A Django module to report issues directly to GitHub.
Home-page: https://github.com/thimpu-create/git_issue_reporter.git
Author: Thimpu Sengyung
Author-email: thmtymthm@gmail.com
Classifier: Development Status :: 3 - Alpha
Classifier: Intended Audience :: Developers
Classifier: License :: OSI Approved :: MIT License
Classifier: Programming Language :: Python :: 3
Classifier: Programming Language :: Python :: 3.11
Classifier: Topic :: Software Development :: Libraries
